{
	"animations": [
		{
			"offsets": [
				0,
				0
			],
			"loop": false,
			"fps": 12,
			"anim": "idle",
			"indices": [],
			"name": "I"
		},
		{
			"offsets": [
				0,
				0
			],
			"loop": false,
			"fps": 12,
			"anim": "singUP",
			"indices": [],
			"name": "U"
		},
		{
			"offsets": [
				0,
				0
			],
			"loop": false,
			"fps": 12,
			"anim": "singRIGHT",
			"indices": [],
			"name": "R"
		},
		{
			"offsets": [
				0,
				0
			],
			"loop": false,
			"fps": 12,
			"anim": "singDOWN",
			"indices": [],
			"name": "D"
		},
		{
			"offsets": [
				0,
				0
			],
			"loop": false,
			"fps": 12,
			"anim": "singLEFT",
			"indices": [],
			"name": "L"
		},
		{
			"loop": false,
			"offsets": [
				0,
				0
			],
			"anim": "hey",
			"fps": 12,
			"name": "H",
			"indices": []
		}
	],
	"vocals_file": "",
	"no_antialiasing": false,
	"image": "characters/daniel",
	"position": [
		-90,
		210
	],
	"healthicon": "bf",
	"flip_x": true,
	"healthbar_colors": [
		49,
		176,
		209
	],
	"camera_position": [
		0,
		0
	],
	"sing_duration": 4,
	"scale": 1,
	"_editor_isPlayer": true
}